 [{
  "title": "Snowy Road",
  "subtitle":"Drive drive drive",
  "image": "photo-1249182325215-d517de72c42d.jpg"
  }, {
  "title": "The Desert",
  "subtitle": "So hot, Much sand",
  "image": "photo-1331975562098-bac8ded504c7.jpg"
  }, {
  "title": "The Green",
  "subtitle": "great escape",
  "image": "photo-1431887773042-803ed52bed26.jpg"  
  }, {
  "title": "Green door",
  "subtitle": "Knock knock",
  "image": "photo-1438190318100-06790c8b2e5a.jpg"
  }, {
  "title": "The Mountain",
  "subtitle": "Outdoor adventure",
  "image": "photo-1443890923422-7819ed4101c0.jpg"
  
  }, {
  "title": "Foggy forest",
  "subtitle": "Demystifying the mist",
  "image": "photo-1445285303476-2f3b16d67b7a.jpg"
  }, {
  "title": "Minimalism",
  "subtitle": "Modern architecture",
  "image": "photo-1446771326090-d910bfaf00f6.jpg"
  }, {
  "title": "Nature",
  "subtitle": "Cross the bridge",
  "image": "photo-1446752875215-b2761acb3c5d.jpg"
  }, {
  "title": "Snowy night",
  "subtitle": "Christmas story",
  "image": "photo-1447877015176-3099cb49cd6a.jpg"
  }, {
  "title": "White & Gold",
  "subtitle": "Architecture",
  "image": "photo-1448318440207-ef1893eb8ac0.jpg"
  }, {
  "title": "Skyline",
  "subtitle": "One night in New-York",
  "image": "photo-1449157291145-7efd050a4d0e.jpg"
  }]